impfxxk.py
impfxxk-0.0.0.dev0.dist-info/LICENSE
impfxxk-0.0.0.dev0.dist-info/METADATA
impfxxk-0.0.0.dev0.dist-info/WHEEL
impfxxk-0.0.0.dev0.dist-info/top_level.txt
impfxxk-0.0.0.dev0.dist-info/zip-safe
impfxxk-0.0.0.dev0.dist-info/RECORD
