Metadata-Version: 2.1
Name: impfxxk
Version: 0.0.0.dev0
Summary: Import for Humans 💅🏻
Home-page: https://github.com/JarryShaw/impfxxk
Author: Jarry Shaw
Author-email: jarryshaw@icloud.com
License: MIT License
Keywords: import metapath
Platform: UNKNOWN
Classifier: Development Status :: 1 - Planning
Classifier: Intended Audience :: Developers
Classifier: License :: OSI Approved :: MIT License
Classifier: Natural Language :: English
Classifier: Operating System :: OS Independent
Classifier: Programming Language :: Python
Classifier: Topic :: Software Development
Classifier: Topic :: Utilities
